{"_type":"export","__export_format":4,"__export_date":"2023-09-20T18:18:38.698Z","__export_source":"insomnia.desktop.app:v2023.5.8","resources":[{"_id":"req_c0748ecda28446d7abff8a6cc0f8d3f4","parentId":"wrk_a02611852bf74214acc7fd8d13b93f3a","modified":1695232488506,"created":1695232001287,"url":"http://localhost:3001/users/nathan","name":"/users/","description":"","method":"GET","body":{},"parameters":[],"headers":[{"name":"User-Agent","value":"insomnia/2023.5.8","id":"pair_3a854599e0394941afacc9d116a699cb"},{"id":"pair_d1133a468057489c9fb46a02a6f70ba2","name":"authorization","value":"Bearer eyJhbGciOiJIUzI1NiIsInR5cCI6IkpXVCJ9.eyJ1c2VybmFtZSI6InRlc3R1c2VyIiwiaXNBZG1pbiI6ZmFsc2UsImlhdCI6MTY5NTIzMTQ1N30._44FVeDJgvJKMUbGEmz1s_hxxc5HOnSholTVoFh3zwE","description":""}],"authentication":{},"metaSortKey":-1695232001287,"isPrivate":false,"settingStoreCookies":true,"settingSendCookies":true,"settingDisableRenderRequestBody":false,"settingEncodeUrl":true,"settingRebuildPath":true,"settingFollowRedirects":"global","_type":"request"},{"_id":"wrk_a02611852bf74214acc7fd8d13b93f3a","parentId":null,"modified":1695231330584,"created":1695231330584,"name":"express-jobly","description":"","scope":"collection","_type":"workspace"},{"_id":"req_5bd2f30325664fdbbbf240ffa0f26326","parentId":"wrk_a02611852bf74214acc7fd8d13b93f3a","modified":1695232449558,"created":1695232274448,"url":"http://localhost:3001/users","name":"/users/","description":"","method":"POST","body":{"mimeType":"application/json","text":"{\n\t\"username\": \"jerry\",\n\t\"password\": \"password\",\n\t\"firstName\": \"Jerry\",\n\t\"lastName\": \"Smith\",\n\t\"email\": \"jerry@gmail.com\",\n\t\"isAdmin\": false\n}"},"parameters":[],"headers":[{"name":"Content-Type","value":"application/json","id":"pair_3bf786d73de54582a8f1c13bd288d0b4"},{"name":"User-Agent","value":"insomnia/2023.5.8","id":"pair_3a854599e0394941afacc9d116a699cb"},{"id":"pair_d1133a468057489c9fb46a02a6f70ba2","name":"authorization","value":"Bearer eyJhbGciOiJIUzI1NiIsInR5cCI6IkpXVCJ9.eyJ1c2VybmFtZSI6Im5hdGhhbiIsImlzQWRtaW4iOmZhbHNlLCJpYXQiOjE2OTUyMzE1NDR9.bznJxhnmNmmyNm4p5ZsF1Q8jvRg9aEavfA5xhyoIrdk","description":""}],"authentication":{},"metaSortKey":-1695231816551,"isPrivate":false,"settingStoreCookies":true,"settingSendCookies":true,"settingDisableRenderRequestBody":false,"settingEncodeUrl":true,"settingRebuildPath":true,"settingFollowRedirects":"global","_type":"request"},{"_id":"req_56c9eca3b56f470188bb679732a4c050","parentId":"wrk_a02611852bf74214acc7fd8d13b93f3a","modified":1695231678664,"created":1695231631815,"url":"http://localhost:3001/companies","name":"/companies/","description":"","method":"GET","body":{},"parameters":[],"headers":[{"name":"User-Agent","value":"insomnia/2023.5.8"}],"authentication":{},"metaSortKey":-1695231631815,"isPrivate":false,"settingStoreCookies":true,"settingSendCookies":true,"settingDisableRenderRequestBody":false,"settingEncodeUrl":true,"settingRebuildPath":true,"settingFollowRedirects":"global","_type":"request"},{"_id":"req_48510cf78674440781d2c03cbc1c6181","parentId":"wrk_a02611852bf74214acc7fd8d13b93f3a","modified":1695231699546,"created":1695231697451,"url":"http://localhost:3001/companies/anderson-arias-morrow","name":"/companies/:handle","description":"","method":"GET","body":{},"parameters":[],"headers":[{"name":"User-Agent","value":"insomnia/2023.5.8"}],"authentication":{},"metaSortKey":-1695231492058,"isPrivate":false,"settingStoreCookies":true,"settingSendCookies":true,"settingDisableRenderRequestBody":false,"settingEncodeUrl":true,"settingRebuildPath":true,"settingFollowRedirects":"global","_type":"request"},{"_id":"req_8e1dc668b83d4e7d9d14e867950bb07c","parentId":"wrk_a02611852bf74214acc7fd8d13b93f3a","modified":1695231464676,"created":1695231352301,"url":"http://localhost:3001/auth/token","name":"/auth/token","description":"","method":"POST","body":{"mimeType":"application/json","text":"{\n\t\"username\": \"testuser\",\n\t\"password\": \"password\"\n}"},"parameters":[],"headers":[{"name":"Content-Type","value":"application/json"},{"name":"User-Agent","value":"insomnia/2023.5.8"}],"authentication":{},"metaSortKey":-1695231352301,"isPrivate":false,"settingStoreCookies":true,"settingSendCookies":true,"settingDisableRenderRequestBody":false,"settingEncodeUrl":true,"settingRebuildPath":true,"settingFollowRedirects":"global","_type":"request"},{"_id":"req_2a01697c16aa44a69d76c157f1feb4e6","parentId":"wrk_a02611852bf74214acc7fd8d13b93f3a","modified":1695231532888,"created":1695231332835,"url":"http://localhost:3001/auth/register","name":"/auth/register","description":"","method":"POST","body":{"mimeType":"application/json","text":"{\n\t\"username\": \"nathan\",\n\t\"password\": \"password\",\n\t\"firstName\": \"Nathan\",\n\t\"lastName\": \"Tjahjadi\",\n\t\"email\": \"nathan@gmail.com\"\n}"},"parameters":[],"headers":[{"name":"Content-Type","value":"application/json"},{"name":"User-Agent","value":"insomnia/2023.5.8"}],"authentication":{},"metaSortKey":-1695231332835,"isPrivate":false,"settingStoreCookies":true,"settingSendCookies":true,"settingDisableRenderRequestBody":false,"settingEncodeUrl":true,"settingRebuildPath":true,"settingFollowRedirects":"global","_type":"request"},{"_id":"env_dc56055aa85b731723bed5bdde95db1eb3fb0913","parentId":"wrk_a02611852bf74214acc7fd8d13b93f3a","modified":1695231330590,"created":1695231330590,"name":"Base Environment","data":{},"dataPropertyOrder":null,"color":null,"isPrivate":false,"metaSortKey":1695231330590,"_type":"environment"},{"_id":"jar_dc56055aa85b731723bed5bdde95db1eb3fb0913","parentId":"wrk_a02611852bf74214acc7fd8d13b93f3a","modified":1695231330591,"created":1695231330591,"name":"Default Jar","cookies":[],"_type":"cookie_jar"}]}